{
  "publicPath": "",
  "all": [
    "resources/client/assets/images/bg-55db3d935f636539072ee47747102459.jpeg",
    "app.16890066.js",
    "vendor.defcc1ef.js",
    "runtime.3f51ee6f.js",
    "styles.90afeb17.css",
    "index.html"
  ],
  "initial": [
    "runtime.3f51ee6f.js",
    "vendor.defcc1ef.js",
    "app.16890066.js"
  ],
  "async": [],
  "modules": {
    "a8bf98f0": [
      1,
      4
    ],
    "c10959b6": [
      1,
      4
    ],
    "17fbcc97": [
      1,
      4
    ],
    "6e080652": [
      2
    ],
    "e03e8946": [
      2
    ],
    "ae9ea1ae": [
      1,
      4
    ],
    "50c6ebad": [
      1,
      4
    ],
    "02b7a2c4": [
      1,
      4
    ],
    "87c5bdfc": [
      1,
      4
    ],
    "663ec05e": [
      1,
      4
    ],
    "604b841e": [
      1,
      4
    ],
    "35cfe1ee": [
      1,
      4
    ],
    "69280d4b": [
      1,
      4
    ],
    "ab81e3d4": [
      2
    ],
    "78a239cc": [
      2
    ],
    "a4114d4a": [
      2
    ],
    "274fa575": [
      1,
      4
    ],
    "19dd5d9c": [
      1,
      4
    ],
    "a18004e6": [
      1,
      4
    ],
    "fd3f4e24": [
      1,
      4
    ],
    "09a120d3": [
      1,
      4
    ],
    "5859e58e": [
      1,
      4
    ],
    "0cbeb630": [
      1,
      4
    ],
    "5a78d43c": [
      1,
      4
    ],
    "217f26c8": [
      1,
      4
    ],
    "67ebe20c": [
      1,
      4
    ],
    "5cc57c16": [
      1,
      4
    ],
    "458be405": [
      1,
      4
    ],
    "4f88054f": [
      1,
      4
    ],
    "281b313c": [
      1,
      4
    ],
    "10e1992b": [
      1,
      4
    ],
    "75b0a024": [
      1,
      4
    ],
    "513537d8": [
      1,
      4
    ],
    "5b961025": [
      1,
      4
    ],
    "5756df8c": [
      1,
      4
    ],
    "4d4b2a5a": [
      1,
      4
    ],
    "7bbe5a7c": [
      1,
      4
    ],
    "476173bc": [
      1,
      4
    ],
    "08b1b102": [
      1,
      4
    ],
    "6f7952ac": [
      1,
      4
    ],
    "586745f2": [
      1,
      4
    ],
    "4340b15a": [
      1,
      4
    ],
    "434125b9": [
      1,
      4
    ],
    "004c80c8": [
      1,
      4
    ],
    "a785ed3e": [
      1,
      4
    ],
    "e7bd7a12": [
      1,
      4
    ],
    "56106ee9": [
      2
    ]
  }
}